fileutil/__init__.py
fileutil/common.py
fileutil/filesplit.py
fileutil/filetransform.py
fileutil/fileunion.py
fileutil/parser.py
fileutil-1.0.4.dist-info/LICENSE.txt
fileutil-1.0.4.dist-info/METADATA
fileutil-1.0.4.dist-info/WHEEL
fileutil-1.0.4.dist-info/top_level.txt
fileutil-1.0.4.dist-info/RECORD
