Metadata-Version: 2.1
Name: fileutil
Version: 1.0.4
Summary: 
Home-page: https://github.com/lurkera/fileutil
Author: Mr linle
Author-email: linle861021@163.com
License: MIT
Platform: all
Requires-Python: >=3
Requires-Dist: cchardet
Requires-Dist: pathlib
Requires-Dist: pandas
Requires-Dist: xlrd
Requires-Dist: numpy
Requires-Dist: xlsxwriter
